airgap_transfer/__init__.py
airgap_transfer/__version__.py
airgap_transfer/cli/__init__.py
airgap_transfer/cli/install.py
airgap_transfer/cli/main.py
airgap_transfer/cli/qr_decode.py
airgap_transfer/cli/qr_encode.py
airgap_transfer/cli/send.py
airgap_transfer/installer/__init__.py
airgap_transfer/installer/packager.py
airgap_transfer/installer/templates/README.txt.tpl
airgap_transfer/installer/templates/bootstrap.sh.tpl
airgap_transfer/installer/templates/qr_sender.py.tpl
airgap_transfer/keyboard/__init__.py
airgap_transfer/keyboard/sender.py
airgap_transfer/qrcode/__init__.py
airgap_transfer/qrcode/decoder.py
airgap_transfer/qrcode/encoder.py
airgap_transfer/utils/__init__.py
airgap_transfer/utils/checksum.py
airgap_transfer/utils/constants.py
airgap_transfer/utils/encoding.py
airgap_transfer-0.1.0.dist-info/METADATA
airgap_transfer-0.1.0.dist-info/WHEEL
airgap_transfer-0.1.0.dist-info/entry_points.txt
airgap_transfer-0.1.0.dist-info/licenses/LICENSE
airgap_transfer-0.1.0.dist-info/RECORD
