Metadata-Version: 2.4
Name: airgap-transfer
Version: 0.1.0
Summary: Bi-directional file transfer tools for air-gapped and isolated environments
Project-URL: Homepage, https://github.com/RLHQ/airgap-transfer
Project-URL: Repository, https://github.com/RLHQ/airgap-transfer.git
Project-URL: Issues, https://github.com/RLHQ/airgap-transfer/issues
Author: airgap-transfer contributors
License: MIT
License-File: LICENSE
Keywords: air-gapped,airgap,bastion,file-transfer,isolated,keyboard-input,qrcode,security,vdi
Classifier: Development Status :: 4 - Beta
Classifier: Intended Audience :: Information Technology
Classifier: Intended Audience :: System Administrators
Classifier: License :: OSI Approved :: MIT License
Classifier: Operating System :: OS Independent
Classifier: Programming Language :: Python :: 3
Classifier: Programming Language :: Python :: 3.9
Classifier: Programming Language :: Python :: 3.10
Classifier: Programming Language :: Python :: 3.11
Classifier: Programming Language :: Python :: 3.12
Classifier: Programming Language :: Python :: 3.13
Classifier: Topic :: Security
Classifier: Topic :: System :: Networking
Classifier: Topic :: System :: Systems Administration
Requires-Python: >=3.9
Requires-Dist: pynput>=1.7.0
Provides-Extra: all
Requires-Dist: opencv-python>=4.5.0; extra == 'all'
Requires-Dist: pyzbar>=0.1.9; extra == 'all'
Requires-Dist: qrcode[pil]>=7.0; extra == 'all'
Provides-Extra: dev
Requires-Dist: black>=23.0; extra == 'dev'
Requires-Dist: build>=0.10.0; extra == 'dev'
Requires-Dist: mypy>=1.0; extra == 'dev'
Requires-Dist: pytest-cov>=4.0; extra == 'dev'
Requires-Dist: pytest>=7.0; extra == 'dev'
Requires-Dist: ruff>=0.1.0; extra == 'dev'
Requires-Dist: twine>=4.0.0; extra == 'dev'
Provides-Extra: qrcode
Requires-Dist: opencv-python>=4.5.0; extra == 'qrcode'
Requires-Dist: pyzbar>=0.1.9; extra == 'qrcode'
Requires-Dist: qrcode[pil]>=7.0; extra == 'qrcode'
